pycocap/__init__.py
pycocap/_version.py
pycocap/pycocap.py
pycocap-1.3.3.dist-info/METADATA
pycocap-1.3.3.dist-info/WHEEL
pycocap-1.3.3.dist-info/top_level.txt
pycocap-1.3.3.dist-info/RECORD
