Metadata-Version: 2.1
Name: pycocap
Version: 1.3.3
Summary: PyCOCAP: The Python interface to the COCAP database
Author-email: Lennart Schüler <lennart.schueler@ufz.de>
Project-URL: Documentation, https://cocap.pages.hzdr.de/pycocap/
Project-URL: Source, https://gitlab.hzdr.de/cocap/pycocap/
Classifier: Development Status :: 4 - Beta
Classifier: Intended Audience :: Developers
Classifier: Intended Audience :: End Users/Desktop
Classifier: Intended Audience :: Science/Research
Classifier: Intended Audience :: Education
Classifier: Natural Language :: English
Classifier: Operating System :: Unix
Classifier: Operating System :: Microsoft
Classifier: Operating System :: MacOS
Classifier: Programming Language :: Python
Classifier: Programming Language :: Python :: 3
Classifier: Programming Language :: Python :: 3 :: Only
Classifier: Programming Language :: Python :: 3.8
Classifier: Programming Language :: Python :: 3.9
Classifier: Programming Language :: Python :: 3.10
Classifier: Topic :: Scientific/Engineering
Requires-Python: >=3.8
Requires-Dist: pandas >=1.4.0
Requires-Dist: requests >=2.27.1
Provides-Extra: doc
Requires-Dist: numpydoc >=1.1 ; extra == 'doc'
Requires-Dist: sphinx >=4 ; extra == 'doc'
Requires-Dist: sphinx-rtd-theme >=1 ; extra == 'doc'
